MANIFEST.in
README.rst
setup.py
django_parsley.egg-info/PKG-INFO
django_parsley.egg-info/SOURCES.txt
django_parsley.egg-info/dependency_links.txt
django_parsley.egg-info/not-zip-safe
django_parsley.egg-info/requires.txt
django_parsley.egg-info/top_level.txt
parsley/__init__.py
parsley/decorators.py
parsley/mixins.py
parsley/models.py
parsley/widgets.py
parsley/static/parsley/js/parsley.django-admin.js
parsley/static/parsley/js/parsley.js
parsley/static/parsley/js/parsley.min.js
parsley/templatetags/__init__.py
parsley/templatetags/parsley.py
parsley/tests/__init__.py
parsley/tests/admin.py
parsley/tests/forms.py
parsley/tests/models.py
parsley/tests/tests.py
parsley/tests/views.py