Metadata-Version: 1.1
Name: django-parsley
Version: 0.7
Summary: Django app for client-side form validation. Wrapper for parsley.js
Home-page: http://github.com/agiliq/django-parsley
Author: Agiliq
Author-email: hello@agiliq.com
License: BSD
Platform: UNKNOWN
Classifier: Development Status :: 3 - Alpha
Classifier: Environment :: Web Environment
Classifier: Intended Audience :: Developers
Classifier: License :: OSI Approved :: BSD License
Classifier: Operating System :: OS Independent
Classifier: Programming Language :: Python
Classifier: Programming Language :: Python :: 3
Classifier: Framework :: Django
